gexecute.py
gexecute-0.1.0.dist-info/LICENSE.txt
gexecute-0.1.0.dist-info/METADATA
gexecute-0.1.0.dist-info/WHEEL
gexecute-0.1.0.dist-info/top_level.txt
gexecute-0.1.0.dist-info/RECORD
