Metadata-Version: 2.1
Name: gexecute
Version: 0.1.0
Summary: Generically execute any function with a unknown function, module, or set of parameters!
Home-page: https://github.com/TimCosby/generic_execute
Author: Tim Cosby
Author-email: tim.cosby0@gmail.com
License: MIT
Keywords: generic execute function module
Platform: UNKNOWN
Classifier: Programming Language :: Python :: 3
Classifier: Programming Language :: Python :: 3.7
Classifier: License :: OSI Approved :: MIT License
Classifier: Operating System :: OS Independent
Requires-Python: >=3.4
Requires-Dist: nest-asyncio
